LICENSE
README.md
setup.py
bin/yaml2gcode
tests/test_dummy.py
yaml2gcode/__init__.py
yaml2gcode/__version__.py
yaml2gcode.egg-info/PKG-INFO
yaml2gcode.egg-info/SOURCES.txt
yaml2gcode.egg-info/dependency_links.txt
yaml2gcode.egg-info/entry_points.txt
yaml2gcode.egg-info/requires.txt
yaml2gcode.egg-info/top_level.txt